README.md
i_lazy/__init__.py
i_lazy/data_structures/__init__.py
i_lazy/data_structures/dict/__init__.py
i_lazy/data_structures/dict/context_dict.py
i_lazy/data_structures/dict/data_schema.py
i_lazy/data_structures/dict/dot_dict.py
i_lazy/data_structures/singleton.py
i_lazy/utils/__init__.py
i_lazy/utils/dict.py
i_lazy/utils/profiling.py
i_lazy/utils/type_ocd.py
i_lazy-0.1.1.dist-info/WHEEL
i_lazy-0.1.1.dist-info/METADATA
i_lazy-0.1.1.dist-info/RECORD
