Metadata-Version: 2.1
Name: i-lazy
Version: 0.1.1
Summary: A small collection of Python laziness.
Home-page: https://github.com/ppeetteerrs/i-lazy-python.git
Keywords: utility,data_structure,helper,simple,common
Author: Peter Yuen
Author-email: ppeetteerrsx@gmail.com
Requires-Python: >=3.8,<4.0
Classifier: Programming Language :: Python :: 3
Classifier: Programming Language :: Python :: 3.10
Classifier: Programming Language :: Python :: 3.8
Classifier: Programming Language :: Python :: 3.9
Requires-Dist: flatdict (>=4.0.1,<5.0.0)
Project-URL: Repository, https://github.com/ppeetteerrs/i-lazy-python.git
